serpentine/__init__.py
serpentine/CRYSTALS/__init__.py
serpentine/CRYSTALS/Kyber/__init__.py
serpentine/CRYSTALS/Kyber/CCAKEM/Kyber1024.py
serpentine/CRYSTALS/Kyber/CCAKEM/Kyber1024_90.py
serpentine/CRYSTALS/Kyber/CCAKEM/Kyber512.py
serpentine/CRYSTALS/Kyber/CCAKEM/Kyber512_90.py
serpentine/CRYSTALS/Kyber/CCAKEM/Kyber768.py
serpentine/CRYSTALS/Kyber/CCAKEM/Kyber768_90.py
serpentine/CRYSTALS/Kyber/CCAKEM/__init__.py
serpentine/CRYSTALS/Kyber/CPAPKE/Kyber1024.py
serpentine/CRYSTALS/Kyber/CPAPKE/Kyber1024_90.py
serpentine/CRYSTALS/Kyber/CPAPKE/Kyber512.py
serpentine/CRYSTALS/Kyber/CPAPKE/Kyber512_90.py
serpentine/CRYSTALS/Kyber/CPAPKE/Kyber768.py
serpentine/CRYSTALS/Kyber/CPAPKE/Kyber768_90.py
serpentine/CRYSTALS/Kyber/CPAPKE/__init__.py
serpentine/CRYSTALS/Kyber/preliminaries/__init__.py
serpentine/CRYSTALS/Kyber/preliminaries/algorithms.py
serpentine/CRYSTALS/Kyber/symmetric_primitives/90s.py
serpentine/CRYSTALS/Kyber/symmetric_primitives/__init__.py
serpentine/CRYSTALS/Kyber/symmetric_primitives/fips_202.py
serpentinite-0.0.1a0.dist-info/LICENSE
serpentinite-0.0.1a0.dist-info/METADATA
serpentinite-0.0.1a0.dist-info/WHEEL
serpentinite-0.0.1a0.dist-info/top_level.txt
serpentinite-0.0.1a0.dist-info/RECORD
