Metadata-Version: 2.1
Name: serpentinite
Version: 0.0.1a0
Summary: Python implementation of CRYSTALS-Kyber post-quantum KEM
Author-email: Alessio Proietti <alessio.proietti@protonmail.com>
License: The MIT License (MIT)
Project-URL: Homepage, https://github.com/alessio-proietti/py-CRYSTALS-kyber
Project-URL: Bug Tracker, https://github.com/alessio-proietti/py-CRYSTALS-kyber/issues
Classifier: Programming Language :: Python :: 3
Classifier: License :: OSI Approved :: MIT License
Classifier: Operating System :: OS Independent
Requires-Python: >=3.7
License-File: LICENSE
